eclipse_nn/LipConstEstimator.py
eclipse_nn/__init__.py
eclipse_nn/eclipsE.py
eclipse_nn/eclipsE_fast.py
eclipse_nn/extract_model_info.py
eclipse_nn-0.1.4.dist-info/licenses/LICENSE
eclipse_nn-0.1.4.dist-info/METADATA
eclipse_nn-0.1.4.dist-info/WHEEL
eclipse_nn-0.1.4.dist-info/top_level.txt
eclipse_nn-0.1.4.dist-info/RECORD
