Metadata-Version: 2.4
Name: eclipse-nn
Version: 0.1.4
Summary: Efficient Compositional Lipschitz Constant Estimation for Deep Neural Networks. Python implementation of the NeurIPS 2024 paper.
Author-email: Hangjun He <hangjun@sas.upenn.edu>
License: MIT License
Project-URL: Homepage, https://github.com/YuezhuXu/ECLipsE
Project-URL: Repository, https://github.com/YuezhuXu/ECLipsE
Requires-Python: >=3.8
License-File: LICENSE
Requires-Dist: numpy
Requires-Dist: torch
Requires-Dist: cvxpy
Requires-Dist: scipy
Dynamic: license-file
